jupyterlab_hybrid_kernels/__init__.py
jupyterlab_hybrid_kernels/_version.py
jupyterlab_hybrid_kernels-0.1.2.data/data/share/jupyter/labextensions/jupyterlab-hybrid-kernels/package.json
jupyterlab_hybrid_kernels-0.1.2.data/data/share/jupyter/labextensions/jupyterlab-hybrid-kernels/schemas/jupyterlab-hybrid-kernels/package.json.orig
jupyterlab_hybrid_kernels-0.1.2.data/data/share/jupyter/labextensions/jupyterlab-hybrid-kernels/schemas/jupyterlab-hybrid-kernels/plugin.json
jupyterlab_hybrid_kernels-0.1.2.data/data/share/jupyter/labextensions/jupyterlab-hybrid-kernels/static/188.f4b31ded8ba5b281c587.js
jupyterlab_hybrid_kernels-0.1.2.data/data/share/jupyter/labextensions/jupyterlab-hybrid-kernels/static/266.5ec2e9d986892b7a5a7c.js
jupyterlab_hybrid_kernels-0.1.2.data/data/share/jupyter/labextensions/jupyterlab-hybrid-kernels/static/385.9308d64ed5723595ec4c.js
jupyterlab_hybrid_kernels-0.1.2.data/data/share/jupyter/labextensions/jupyterlab-hybrid-kernels/static/468.7cba51b5a34fb171be6f.js
jupyterlab_hybrid_kernels-0.1.2.data/data/share/jupyter/labextensions/jupyterlab-hybrid-kernels/static/628.8b173c7a164933ab88e7.js
jupyterlab_hybrid_kernels-0.1.2.data/data/share/jupyter/labextensions/jupyterlab-hybrid-kernels/static/644.bfcde403bf5371ceca5c.js
jupyterlab_hybrid_kernels-0.1.2.data/data/share/jupyter/labextensions/jupyterlab-hybrid-kernels/static/728.9c2b98031d0dc76f6f8d.js
jupyterlab_hybrid_kernels-0.1.2.data/data/share/jupyter/labextensions/jupyterlab-hybrid-kernels/static/766.9308d64ed5723595ec4c.js
jupyterlab_hybrid_kernels-0.1.2.data/data/share/jupyter/labextensions/jupyterlab-hybrid-kernels/static/885.5ec2e9d986892b7a5a7c.js
jupyterlab_hybrid_kernels-0.1.2.data/data/share/jupyter/labextensions/jupyterlab-hybrid-kernels/static/remoteEntry.34487d1cec8a6448edc8.js
jupyterlab_hybrid_kernels-0.1.2.data/data/share/jupyter/labextensions/jupyterlab-hybrid-kernels/static/service-worker.js
jupyterlab_hybrid_kernels-0.1.2.dist-info/METADATA
jupyterlab_hybrid_kernels-0.1.2.dist-info/WHEEL
jupyterlab_hybrid_kernels-0.1.2.dist-info/licenses/LICENSE
jupyterlab_hybrid_kernels-0.1.2.dist-info/RECORD
